MANIFEST.in
README
setup.py
monocle_snbl/__init__.py
monocle_snbl/controller.py
monocle_snbl/flogger.py
monocle_snbl/mwmonocle.py
monocle_snbl/wdir.py
monocle_snbl.egg-info/PKG-INFO
monocle_snbl.egg-info/SOURCES.txt
monocle_snbl.egg-info/dependency_links.txt
monocle_snbl.egg-info/entry_points.txt
monocle_snbl.egg-info/requires.txt
monocle_snbl.egg-info/top_level.txt
monocle_snbl/ui/__init__.py
monocle_snbl/ui/resources_rc.py
monocle_snbl/ui/ui_mwmonocle.py
monocle_snbl/ui/ui_wdir.py
ui/images/monocle.png