Metadata-Version: 1.1
Name: monocle-snbl
Version: 2018.3.28
Summary: SNBL monochromator watchdog
Home-page: https://hg.3lp.cx/monocle
Author: Vadim Dyadkin
Author-email: diadkin@esrf.fr
License: GPLv3
Platform: UNKNOWN
Classifier: License :: OSI Approved :: GNU General Public License v3 (GPLv3)
Classifier: Programming Language :: Python
Classifier: Programming Language :: Python :: 3.6
Classifier: Programming Language :: Python :: Implementation :: CPython
